<?xml version="1.0" encoding="UTF-8"?>
<objects serializationModel="Studio.02.02.00">
	<object class="AudioFile" id="{b99fd90c-b644-4b07-ad24-12bfefe1e7a2}">
		<property name="assetPath">
			<value>Voice Hit 2.ogg</value>
		</property>
		<property name="frequencyInKHz">
			<value>48</value>
		</property>
		<property name="channelCount">
			<value>2</value>
		</property>
		<property name="length">
			<value>0.53137500000000004</value>
		</property>
		<relationship name="masterAssetFolder">
			<destination>{b9d59c25-4077-4fb4-a32f-05c357b7907f}</destination>
		</relationship>
	</object>
</objects>
